[
  {
    "id": 1,
    "submission_id": "602df47a58bea50c94243d15",
    "asunto": "activacion de compras por internet",
    "content": "Este es un mensaje de prueba",
    "conversation_id": 123456,
    "fecha": "2021-02-18T04:35:20.380Z",
    "conversation": "Esta es una respuesta de prueba",
    "user_id": 123,
    "status_msj": "send"
  },
  {
    "id": 2,
    "submission_id": "602df47a58bea50c94243d16",
    "asunto": "activacion de compras",
    "content": "Este es un mensaje de prueba",
    "conversation_id": 123457,
    "fecha": "2021-03-18T04:35:20.380Z",
    "conversation": "Esta es una respuesta de prueba",
    "user_id": 124,
    "status_msj": "send"
  },
  {
    "id": 3,
    "submission_id": "602df47a58bea50c94243d17",
    "asunto": "verificar saldo",
    "content": "Este es un mensaje de prueba",
    "conversation_id": 123458,
    "fecha": "2021-03-19T04:35:20.380Z",
    "conversation": "Esta es una respuesta de prueba",
    "user_id": 125,
    "status_msj": "send"
  },
  {
    "id": 4,
    "submission_id": "602df47a58bea50c94243d18",
    "asunto": "activacion de compras por internet",
    "content": "Este es un mensaje de prueba",
    "conversation_id": 123459,
    "fecha": "2021-03-20T04:35:20.380Z",
    "conversation": "Esta es una respuesta de prueba",
    "user_id": 126,
    "status_msj": "send"
  },
  {
    "id": 5,
    "submission_id": "602df47a58bea50c94243d20",
    "asunto": "conformar cheque",
    "content": "Este es un mensaje de prueba",
    "conversation_id": 123460,
    "fecha": "2021-03-21T04:35:20.380Z",
    "conversation": "Esta es una respuesta de prueba",
    "user_id": 130,
    "status_msj": "send"
  }
]
